odoo9_addon_web_widget_x2many_2d_matrix-9.0.1.0.0.99.dev13-nspkg.pth
odoo_addons/web_widget_x2many_2d_matrix/README.rst
odoo_addons/web_widget_x2many_2d_matrix/__init__.py
odoo_addons/web_widget_x2many_2d_matrix/__openerp__.py
odoo_addons/web_widget_x2many_2d_matrix/i18n/ar.po
odoo_addons/web_widget_x2many_2d_matrix/i18n/de.po
odoo_addons/web_widget_x2many_2d_matrix/i18n/es.po
odoo_addons/web_widget_x2many_2d_matrix/i18n/fi.po
odoo_addons/web_widget_x2many_2d_matrix/i18n/fr.po
odoo_addons/web_widget_x2many_2d_matrix/i18n/hr.po
odoo_addons/web_widget_x2many_2d_matrix/i18n/it.po
odoo_addons/web_widget_x2many_2d_matrix/i18n/pt_BR.po
odoo_addons/web_widget_x2many_2d_matrix/i18n/sl.po
odoo_addons/web_widget_x2many_2d_matrix/i18n/tr.po
odoo_addons/web_widget_x2many_2d_matrix/readme/CONTRIBUTORS.rst
odoo_addons/web_widget_x2many_2d_matrix/readme/DESCRIPTION.rst
odoo_addons/web_widget_x2many_2d_matrix/readme/ROADMAP.rst
odoo_addons/web_widget_x2many_2d_matrix/readme/USAGE.rst
odoo_addons/web_widget_x2many_2d_matrix/static/description/icon.png
odoo_addons/web_widget_x2many_2d_matrix/static/description/index.html
odoo_addons/web_widget_x2many_2d_matrix/static/description/screenshot.png
odoo_addons/web_widget_x2many_2d_matrix/static/src/css/web_widget_x2many_2d_matrix.css
odoo_addons/web_widget_x2many_2d_matrix/static/src/js/web_widget_x2many_2d_matrix.js
odoo_addons/web_widget_x2many_2d_matrix/static/src/xml/web_widget_x2many_2d_matrix.xml
odoo_addons/web_widget_x2many_2d_matrix/views/templates.xml
odoo9_addon_web_widget_x2many_2d_matrix-9.0.1.0.0.99.dev13.dist-info/METADATA
odoo9_addon_web_widget_x2many_2d_matrix-9.0.1.0.0.99.dev13.dist-info/WHEEL
odoo9_addon_web_widget_x2many_2d_matrix-9.0.1.0.0.99.dev13.dist-info/namespace_packages.txt
odoo9_addon_web_widget_x2many_2d_matrix-9.0.1.0.0.99.dev13.dist-info/top_level.txt
odoo9_addon_web_widget_x2many_2d_matrix-9.0.1.0.0.99.dev13.dist-info/RECORD
